foundation/__init__.py
foundation/static/foundation/LICENSE
foundation/static/foundation/_vendor/sassy-lists/stylesheets/functions/_contain.scss
foundation/static/foundation/_vendor/sassy-lists/stylesheets/functions/_purge.scss
foundation/static/foundation/_vendor/sassy-lists/stylesheets/functions/_remove.scss
foundation/static/foundation/_vendor/sassy-lists/stylesheets/functions/_replace.scss
foundation/static/foundation/_vendor/sassy-lists/stylesheets/functions/_to-list.scss
foundation/static/foundation/_vendor/sassy-lists/stylesheets/helpers/_missing-dependencies.scss
foundation/static/foundation/_vendor/sassy-lists/stylesheets/helpers/_true.scss
foundation/static/foundation/css/foundation-float.css
foundation/static/foundation/css/foundation-float.css.map
foundation/static/foundation/css/foundation-float.min.css
foundation/static/foundation/css/foundation-float.min.css.map
foundation/static/foundation/css/foundation-icons.css
foundation/static/foundation/css/foundation-icons.eot
foundation/static/foundation/css/foundation-icons.svg
foundation/static/foundation/css/foundation-icons.ttf
foundation/static/foundation/css/foundation-icons.woff
foundation/static/foundation/css/foundation-prototype.css
foundation/static/foundation/css/foundation-prototype.css.map
foundation/static/foundation/css/foundation-prototype.min.css
foundation/static/foundation/css/foundation-prototype.min.css.map
foundation/static/foundation/css/foundation-rtl.css
foundation/static/foundation/css/foundation-rtl.css.map
foundation/static/foundation/css/foundation-rtl.min.css
foundation/static/foundation/css/foundation-rtl.min.css.map
foundation/static/foundation/css/foundation.css
foundation/static/foundation/css/foundation.css.map
foundation/static/foundation/css/foundation.min.css
foundation/static/foundation/css/foundation.min.css.map
foundation/static/foundation/js/foundation.cjs.js
foundation/static/foundation/js/foundation.cjs.js.map
foundation/static/foundation/js/foundation.d.ts
static_foundation-6.6.3.dist-info/METADATA
static_foundation-6.6.3.dist-info/WHEEL
static_foundation-6.6.3.dist-info/top_level.txt
static_foundation-6.6.3.dist-info/RECORD
