Metadata-Version: 2.1
Name: static-foundation
Version: 6.6.3
Summary: Django Zurb Foundation + Motion-UI package
Home-page: https://github.com/wtayyeb/static-foundation
Author: w.tayyeb
Author-email: w.tayyeb@gmail.com
License: BSD License
Platform: UNKNOWN
Classifier: Environment :: Web Environment
Classifier: Framework :: Django
Classifier: Intended Audience :: Developers
Classifier: License :: OSI Approved :: BSD License
Classifier: Operating System :: OS Independent
Classifier: Programming Language :: Python
Classifier: Programming Language :: Python :: 2
Classifier: Programming Language :: Python :: 3
Classifier: Topic :: Utilities
